[
  {
    "fixture": "indicator_strategy_long_allowed.pine",
    "expected": "ok",
    "observed_status": "ok",
    "has_error": false,
    "has_compiled": true,
    "interesting_tail": [
      "Compiling...",
      "13:55:12Compiled.",
      "Compiled.",
      "indicator strategy.long constant",
      "indicator(\"indicator strategy.long constant\")",
      "dir = strategy.long"
    ]
  },
  {
    "fixture": "library_strategy_long_allowed.pine",
    "expected": "ok",
    "observed_status": "ok",
    "has_error": false,
    "has_added_or_compiled": true,
    "interesting_tail": [
      "Compiling...",
      "13:51:59Compiled.",
      "Compiled.",
      "13:51:59Added to chart.",
      "Added to chart.",
      "export f() => strategy.long"
    ]
  },
  {
    "fixture": "indicator_strategy_equity_forbidden.pine",
    "expected": "invalid_expected",
    "observed_status": "invalid_expected",
    "has_error": true,
    "has_compiled": false,
    "interesting_tail": [
      "Compiling...",
      "13:53:35Error at 2:1 You cannot use strategy functions (strategy.equity) in indicator script. Please replace \"indicator\" with \"strategy\".",
      "Error at 2:1 You cannot use strategy functions (strategy.equity) in indicator script. Please replace \"indicator\" with \"strategy\".",
      "Error at 2:1",
      "Error at 2:1",
      "indicator strategy.long constant",
      "indicator(\"indicator strategy.equity forbidden\")",
      "x = strategy.equity",
      "1 of 1 problem",
      "You cannot use strategy functions (strategy.equity) in indicator script. Please replace \"indicator\" with \"strategy\".(CE10027)"
    ]
  },
  {
    "fixture": "strategy_closedtrades_allowed.pine",
    "expected": "ok",
    "observed_status": "ok",
    "has_error": false,
    "has_compiled": true,
    "interesting_tail": [
      "Compiling...",
      "13:54:28Compiled.",
      "Compiled.",
      "price = strategy.closedtrades.entry_price(0)",
      "comment = strategy.closedtrades.entry_comment(0)"
    ]
  },
  {
    "fixture": "indicator_closedtrades_forbidden.pine",
    "expected": "invalid_expected",
    "observed_status": "invalid_expected",
    "has_error": true,
    "has_compiled": false,
    "interesting_tail": [
      "Compiling...",
      "13:54:39Error at 2:1 You cannot use strategy functions (strategy.closedtrades.entry_price) in indicator script. Please replace \"indicator\" with \"strategy\".",
      "Error at 2:1 You cannot use strategy functions (strategy.closedtrades.entry_price) in indicator script. Please replace \"indicator\" with \"strategy\".",
      "Error at 2:1",
      "Error at 2:1",
      "indicator strategy.long constant",
      "price = strategy.closedtrades.entry_price(0)",
      "1 of 1 problem",
      "You cannot use strategy functions (strategy.closedtrades.entry_price) in indicator script. Please replace \"indicator\" with \"strategy\".(CE10027)"
    ]
  }
]